quantaxisbackend/__init__.py
quantaxisbackend/app.py
quantaxisbackend/backtest/__init__.py
quantaxisbackend/backtest/handles.py
quantaxisbackend/data/__init__.py
quantaxisbackend/data/handles.py
quantaxisbackend/quotation/__init__.py
quantaxisbackend/quotation/handles.py
quantaxisbackend/user/__init__.py
quantaxisbackend/user/handles.py
quantaxisbackend/util/__init__.py
quantaxisbackend/util/handles.py
quantaxisbackend-0.1.0.dist-info/DESCRIPTION.rst
quantaxisbackend-0.1.0.dist-info/METADATA
quantaxisbackend-0.1.0.dist-info/RECORD
quantaxisbackend-0.1.0.dist-info/WHEEL
quantaxisbackend-0.1.0.dist-info/metadata.json
quantaxisbackend-0.1.0.dist-info/top_level.txt
quantaxisbackend-0.1.0.dist-info/zip-safe
