Metadata-Version: 2.0
Name: quantaxisbackend
Version: 0.1.0
Summary: QUANTAXISBACKEND: WEB
Home-page: http://www.yutiansut.com
Author: yutiansut
Author-email: yutiansut@qq.com
License: MIT
Keywords: quantaxis,quant,finance
Platform: UNKNOWN
Classifier: License :: OSI Approved :: MIT License
Classifier: Programming Language :: Python
Classifier: Intended Audience :: Developers
Classifier: Operating System :: OS Independent
Requires-Dist: tornado
